nlpyutil/__init__.py
nlpyutil/argparser.py
nlpyutil/ch_utils.py
nlpyutil/decorators.py
nlpyutil/exceptions.py
nlpyutil/file_util.py
nlpyutil/localize.py
nlpyutil/logger.py
nlpyutil/memorize.py
nlpyutil/preprocess.py
nlpyutil/rarewords.py
nlpyutil/singleton.py
nlpyutil/stopwords.py
nlpyutil/usual_pattern.py
nlpyutil-0.5.0.dist-info/LICENSE
nlpyutil-0.5.0.dist-info/METADATA
nlpyutil-0.5.0.dist-info/WHEEL
nlpyutil-0.5.0.dist-info/top_level.txt
nlpyutil-0.5.0.dist-info/RECORD
